total_perspective_vortex-3.1.3.dist-info/licenses/LICENSE
tpv/__init__.py
tpv/commands/__init__.py
tpv/commands/dryrunner.py
tpv/commands/formatter.py
tpv/commands/linter.py
tpv/commands/mypychecker.py
tpv/commands/shell.py
tpv/commands/type_check_template.j2
tpv/commands/test/__init__.py
tpv/commands/test/mock_galaxy.py
tpv/core/__init__.py
tpv/core/entities.py
tpv/core/evaluator.py
tpv/core/helpers.py
tpv/core/loader.py
tpv/core/mapper.py
tpv/core/resource_requirements.py
tpv/core/util.py
tpv/rules/__init__.py
tpv/rules/gateway.py
total_perspective_vortex-3.1.3.dist-info/METADATA
total_perspective_vortex-3.1.3.dist-info/WHEEL
total_perspective_vortex-3.1.3.dist-info/entry_points.txt
total_perspective_vortex-3.1.3.dist-info/top_level.txt
total_perspective_vortex-3.1.3.dist-info/RECORD
