Metadata-Version: 2.4
Name: total-perspective-vortex
Version: 3.1.3
Summary: A library for routing entities (jobs, users or groups) to destinations in Galaxy
Author: Galaxy Contributors
Maintainer-email: Galaxy Committers <galaxy-committers@lists.galaxyproject.org>
License-Expression: MIT
Project-URL: Homepage, https://github.com/galaxyproject/total-perspective-vortex
Project-URL: Documentation, https://total-perspective-vortex.readthedocs.io
Requires-Python: >=3.9
License-File: LICENSE
Requires-Dist: cachetools>=3.1.0
Requires-Dist: types-cachetools
Requires-Dist: watchdog
Requires-Dist: requests
Requires-Dist: ruamel.yaml
Requires-Dist: mypy
Requires-Dist: jinja2
Requires-Dist: types-requests
Provides-Extra: cli
Requires-Dist: total-perspective-vortex; extra == "cli"
Requires-Dist: galaxy; extra == "cli"
Provides-Extra: test
Requires-Dist: total-perspective-vortex[cli]; extra == "test"
Requires-Dist: pytest; extra == "test"
Requires-Dist: responses; extra == "test"
Requires-Dist: tox>=2.9.1; extra == "test"
Requires-Dist: coverage>=4.4.1; extra == "test"
Provides-Extra: dev
Requires-Dist: total-perspective-vortex[test]; extra == "dev"
Requires-Dist: sphinx; extra == "dev"
Requires-Dist: sphinx_rtd_theme; extra == "dev"
Dynamic: license-file
